wpdm/__init__.py
wpdm/models.py
wpdm/utils.py
template_wpdm-0.1.0.dist-info/LICENSE
template_wpdm-0.1.0.dist-info/METADATA
template_wpdm-0.1.0.dist-info/WHEEL
template_wpdm-0.1.0.dist-info/top_level.txt
template_wpdm-0.1.0.dist-info/RECORD
